{
    "app_config": {
        "audio_config": {
            "audio": "pipewire"
        },
        "bluetooth_config": {
            "enabled": true
        },
        "firewall_config": {
            "firewall": "ufw"
        },
        "print_service_config": {
            "enabled": false
        }
    },
    "archinstall-language": "English",
    "auth_config": {},
    "bootloader_config": {
        "bootloader": "Grub",
        "removable": false,
        "uki": false
    },
    "custom_commands": [],
    "disk_config": {},
    "hostname": "FIXME",
    "kernels": [
        "linux"
    ],
    "locale_config": {
        "kb_layout": "no",
        "sys_enc": "UTF-8",
        "sys_lang": "en_GB.UTF-8"
    },
    "mirror_config": {
        "custom_repositories": [],
        "custom_servers": [],
        "mirror_regions": {
            "Norway": [
                "http://mirror.archlinux.no/$repo/os/$arch",
                "https://mirror.archlinux.no/$repo/os/$arch",
                "http://archlinux.uib.no/$repo/os/$arch",
                "http://mirror.neuf.no/archlinux/$repo/os/$arch",
                "https://mirror.neuf.no/archlinux/$repo/os/$arch",
                "https://archlinux.lysakermoen.com/$repo/os/$arch",
                "http://no.mirror.cx/archlinux/$repo/os/$arch",
                "https://no.mirror.cx/archlinux/$repo/os/$arch"
            ]
        },
        "optional_repositories": [
            "multilib"
        ]
    },
    "network_config": {
        "type": "nm"
    },
    "ntp": true,
    "packages": [
        "gcc",
        "openssh",
        "plocate",
        "qrencode",
        "rustup",
        "zip",
        "7zip",
        "unzip",
        "zsh",
        "git",
        "make",
        "cmake",
        "firefox",
        "jq",
        "fzf",
        "ripgrep",
        "node",
        "zellij",
        "lua-language-server",
        "clang",
        "lua",
        "python",
        "python-pip",
        "curl",
        "wget",
        "fastfetch",
        "base-devel",
        "fakeroot",
        "man-db",
        "man-pages",
        "yt-dlp"
    ],
    "pacman_config": {
        "color": true,
        "parallel_downloads": 5
    },
    "profile_config": {},
    "script": null,
    "services": [],
    "swap": {
        "algorithm": "zstd",
        "enabled": true
    },
    "timezone": "Europe/Oslo",
    "version": "4.3"
}
